flatdata/lib/__init__.py
flatdata/lib/archive.py
flatdata/lib/archive_builder.py
flatdata/lib/data_access.py
flatdata/lib/errors.py
flatdata/lib/file_resource_storage.py
flatdata/lib/file_resource_writer.py
flatdata/lib/flatdata_writer.py
flatdata/lib/inspector.py
flatdata/lib/resource_storage.py
flatdata/lib/resources.py
flatdata/lib/structure.py
flatdata/lib/tar_archive_resource_storage.py
flatdata/lib/writer.py
flatdata_py-0.4.7.dist-info/METADATA
flatdata_py-0.4.7.dist-info/WHEEL
flatdata_py-0.4.7.dist-info/entry_points.txt
flatdata_py-0.4.7.dist-info/RECORD
