Metadata-Version: 2.3
Name: flatdata-py
Version: 0.4.7
Summary: Python 3 implementation of Flatdata
Project-URL: Homepage, https://github.com/heremaps/flatdata
Author: Flatdata Developers
Classifier: License :: OSI Approved :: Apache Software License
Classifier: Operating System :: OS Independent
Classifier: Programming Language :: Python :: 3
Requires-Dist: flatdata-generator==0.4.6
Requires-Dist: numpy
Requires-Dist: pandas
Provides-Extra: inspector
Requires-Dist: ipython; extra == 'inspector'
